{"id":750741,"competencia":{"codigoTabla":null,"codigoValor":1,"codigoRelacion":190001,"valor":"COMPETENCIA ORIGINARIA","activo":"S","usuarioCreacion":"ADMIN","usuarioMod":"ADMIN","fechaCreacionLong":201008231249,"fechaModLong":201008231250,"orden":null,"visible":null},"tipoAccion":null,"sentidoPronunciamiento":{"codigoTabla":null,"codigoValor":7,"codigoRelacion":80007,"valor":"DECLARA COMPETENCIA","activo":"S","usuarioCreacion":"ADMIN","usuarioMod":"ADMIN","fechaCreacionLong":201008181306,"fechaModLong":201008181306,"orden":null,"visible":null},"materia":{"codigoTabla":null,"codigoValor":381,"codigoRelacion":90381,"valor":"CONSTITUCIONAL","activo":"S","usuarioCreacion":"ADMIN","usuarioMod":"SJC287","fechaCreacionLong":201903220948,"fechaModLong":201909170908,"orden":null,"visible":null},"remision":null,"tipoRecurso":null,"dependencia":null,"dependenciaHija":null,"publico":"S","materiaSecretaria":{"codigoTabla":null,"codigoValor":8,"codigoRelacion":250008,"valor":"Originarios","activo":"S","usuarioCreacion":"ADMIN","usuarioMod":"ADMIN","fechaCreacionLong":201604041608,"fechaModLong":201604111334,"orden":null,"visible":null},"caratulaFallo":"Unión Cívica Radical de la Provincia de La Rioja y otro c/ La Rioja, Provincia de s/ amparo ","alias":null,"caratula":"UNION CIVICA RADICAL DE LA PROVINCIA DE LA RIOJA Y OTRO c/ LA RIOJA, PROVINCIA DE s/AMPARO","inconstitucional":false,"falloDestacado":{"id":690,"titulo":"Competencia originaria de la Corte frente al conflicto suscitado por una enmienda constitucional. ","cabecilla":"<p>Provincia de La Rioja - Impugnaci&oacute;n de actos emanados de los poderes constituidos de la provincia - Cuesti&oacute;n federal predominante y provincia demandada - Competencia originaria de la Corte - Sustanciaci&oacute;n a trav&eacute;s de las normas que regulan la acci&oacute;n de amparo en virtud de encontrarse en curso un cronograma electoral con plazos breves</p>","esNovedad":true,"fecha":1551409200000,"relevancia":1,"usuarioModificacion":13,"fechaModificacion":1599517897716,"usuarioCreacion":null,"fechaCreacion":null,"privado":null,"posicion":null,"resumen":null},"reciboEntrada":{"id":25511,"secretaria":{"id":15,"tipo":"S","descripcion":"Sec. Juicios Originarios","orden":8,"activo":"S","codigoRelacion":250008,"descripcionWeb":"Originarios","descripcionVacia":""},"reciboEntradaExpedientes":[{"expediente":{"id":33124036,"numeroExpediente":125,"anioExpediente":2019,"tomoExpediente":null,"letraExpediente":null,"tipoExpediente":null,"camara":{"id":0,"codigo":"0","abreviatura":"CSJ","descripcion":"Corte Suprema de Justicia de la Nación","estado":0,"descripcionLarga":"CSJ - Corte Suprema de Justicia de la Nación"},"objetoJuicio":{"id":9875,"descripcion":"AMPARO","idMateria":0,"tema":null},"caratula":"UNION CIVICA RADICAL DE LA PROVINCIA DE LA RIOJA Y OTRO c/ LA RIOJA, PROVINCIA DE s/AMPARO","verificacionMesa":"N","etiqueta":null,"hijos":[],"oldIdentificadorExpediente":"125. "},"recurso":{"id":5526217,"expediente":{"id":33124036,"numeroExpediente":125,"anioExpediente":2019,"tomoExpediente":null,"letraExpediente":null,"tipoExpediente":null,"camara":{"id":0,"codigo":"0","abreviatura":"CSJ","descripcion":"Corte Suprema de Justicia de la Nación","estado":0,"descripcionLarga":"CSJ - Corte Suprema de Justicia de la Nación"},"objetoJuicio":{"id":9875,"descripcion":"AMPARO","idMateria":0,"tema":null},"caratula":"UNION CIVICA RADICAL DE LA PROVINCIA DE LA RIOJA Y OTRO c/ LA RIOJA, PROVINCIA DE s/AMPARO","verificacionMesa":"N","etiqueta":null,"hijos":[],"oldIdentificadorExpediente":"125. "},"tipoRecurso":{"id":1243,"codigo":"CIR","descripcion":"CIRCULACION DEL EXPEDIENTE"},"claveRecurso":null,"identificacionExpediente":"CSJ 125/2019"},"piezas":1,"urgente":"N","observaciones":null,"usuarioCreacion":null,"usuarioCreacionOld":"JUR202","usuarioModificacion":null,"usuarioModificacionOld":"JUR202","fechaCreacion":201902281509,"fechaModificacion":201902281509}],"fecha":1551322800000,"fechaLong":20190228,"observaciones":null,"codigoUsuario":"JUR202","fechaString":"28/02/2019"},"observaciones":null,"comentarios":null,"enPreparacion":null,"formulaDesarrollo":null,"audPublica":"N","articulo16Ley48":"N","inicializacion":"N","amicue_curie":"N","conOpinion":null,"chequeoVoto":"S","cambiaJurisp":null,"sentenciaModelo":null,"citaDoctrina":null,"citaExtranjera":null,"votosOpinion":"N","art11Acordada4":null,"resolucionOriginarios":null,"cuestionesFederales":[],"formulas":[],"recusExcus":[],"voces":[{"tipoVoz":{"codigoTabla":null,"codigoValor":966,"codigoRelacion":100966,"valor":"COMPETENCIA ORIGINARIA DE LA CORTE SUPREMA","activo":"S","usuarioCreacion":"ADMIN","usuarioMod":"ADMIN","fechaCreacionLong":201006301000,"fechaModLong":201006301000,"orden":null,"visible":null},"orden":1,"usuarioCreacion":"JURJ3F","usuarioModificacion":"JURJ3F","fechaCreacion":202003040940,"fechaModificacion":202003040940},{"tipoVoz":{"codigoTabla":null,"codigoValor":472,"codigoRelacion":100472,"valor":"ACCION DE AMPARO","activo":"S","usuarioCreacion":"ADMIN","usuarioMod":"ADMIN","fechaCreacionLong":201006301000,"fechaModLong":201006301000,"orden":null,"visible":null},"orden":2,"usuarioCreacion":"JURJ3F","usuarioModificacion":"JURJ3F","fechaCreacion":202003040940,"fechaModificacion":202003040940},{"tipoVoz":{"codigoTabla":null,"codigoValor":1645,"codigoRelacion":101645,"valor":"ELECCIONES","activo":"S","usuarioCreacion":"ADMIN","usuarioMod":"ADMIN","fechaCreacionLong":201006301000,"fechaModLong":201006301000,"orden":null,"visible":null},"orden":3,"usuarioCreacion":"JURJ3F","usuarioModificacion":"JURJ3F","fechaCreacion":202003040940,"fechaModificacion":202003040940},{"tipoVoz":{"codigoTabla":null,"codigoValor":1103,"codigoRelacion":101103,"valor":"CONSTITUCIONES PROVINCIALES","activo":"S","usuarioCreacion":"ADMIN","usuarioMod":"ADMIN","fechaCreacionLong":201006301000,"fechaModLong":201006301000,"orden":null,"visible":null},"orden":4,"usuarioCreacion":"JURJ3F","usuarioModificacion":"JURJ3F","fechaCreacion":202003040940,"fechaModificacion":202003040940},{"tipoVoz":{"codigoTabla":null,"codigoValor":4175,"codigoRelacion":104175,"valor":"CASO O CONTROVERSIA","activo":"S","usuarioCreacion":"JUR0V0","usuarioMod":"JUR0V0","fechaCreacionLong":201203141528,"fechaModLong":201203141528,"orden":null,"visible":null},"orden":5,"usuarioCreacion":"JURJ3F","usuarioModificacion":"JURJ3F","fechaCreacion":202003040940,"fechaModificacion":202003040940},{"tipoVoz":{"codigoTabla":null,"codigoValor":2969,"codigoRelacion":102969,"valor":"PODER JUDICIAL","activo":"S","usuarioCreacion":"ADMIN","usuarioMod":"ADMIN","fechaCreacionLong":201006301000,"fechaModLong":201006301000,"orden":null,"visible":null},"orden":6,"usuarioCreacion":"JURJ3F","usuarioModificacion":"JURJ3F","fechaCreacion":202003040940,"fechaModificacion":202003040940},{"tipoVoz":{"codigoTabla":null,"codigoValor":4962,"codigoRelacion":104962,"valor":"(*)","activo":"S","usuarioCreacion":"JUR0V0","usuarioMod":"ADMIN","fechaCreacionLong":201903201120,"fechaModLong":201906141011,"orden":null,"visible":null},"orden":7,"usuarioCreacion":"JURJ3F","usuarioModificacion":"JURJ3F","fechaCreacion":202003040940,"fechaModificacion":202003040940},{"tipoVoz":{"codigoTabla":null,"codigoValor":4965,"codigoRelacion":104965,"valor":"(.)","activo":"S","usuarioCreacion":"JUR0V0","usuarioMod":"ADMIN","fechaCreacionLong":201903201221,"fechaModLong":201906141011,"orden":null,"visible":null},"orden":8,"usuarioCreacion":"JURJ3F","usuarioModificacion":"JURJ3F","fechaCreacion":202003040940,"fechaModificacion":202003040940}],"referenciasNormativas":[{"interno":1,"norma":{"codigoTabla":null,"codigoValor":2,"codigoRelacion":110002,"valor":"CONSTITUCION NACIONAL","activo":"S","usuarioCreacion":"ADMIN","usuarioMod":"ADMIN","fechaCreacionLong":201006231357,"fechaModLong":201006231357,"orden":1,"visible":"CN"},"numeroNorma":null,"anioNorma":null,"denominacion":null,"emisor":null,"jurisdiccion":null,"articulo":"1","parrafo":null,"inciso":null,"apartado":null,"controlConstitucional":"N","inconstitucional":"N","usuarioCreacion":"JUR202","usuarioModificacion":"JUR202","fechaCreacion":201902281511,"fechaModificacion":201902281511},{"interno":2,"norma":{"codigoTabla":null,"codigoValor":2,"codigoRelacion":110002,"valor":"CONSTITUCION NACIONAL","activo":"S","usuarioCreacion":"ADMIN","usuarioMod":"ADMIN","fechaCreacionLong":201006231357,"fechaModLong":201006231357,"orden":1,"visible":"CN"},"numeroNorma":null,"anioNorma":null,"denominacion":null,"emisor":null,"jurisdiccion":null,"articulo":"5","parrafo":null,"inciso":null,"apartado":null,"controlConstitucional":"N","inconstitucional":"N","usuarioCreacion":"JUR202","usuarioModificacion":"JUR202","fechaCreacion":201902281512,"fechaModificacion":201902281512},{"interno":3,"norma":{"codigoTabla":null,"codigoValor":2,"codigoRelacion":110002,"valor":"CONSTITUCION NACIONAL","activo":"S","usuarioCreacion":"ADMIN","usuarioMod":"ADMIN","fechaCreacionLong":201006231357,"fechaModLong":201006231357,"orden":1,"visible":"CN"},"numeroNorma":null,"anioNorma":null,"denominacion":null,"emisor":null,"jurisdiccion":null,"articulo":"123","parrafo":null,"inciso":null,"apartado":null,"controlConstitucional":"N","inconstitucional":"N","usuarioCreacion":"JUR202","usuarioModificacion":"JUR202","fechaCreacion":201902281512,"fechaModificacion":201902281512},{"interno":4,"norma":{"codigoTabla":null,"codigoValor":3,"codigoRelacion":110003,"valor":"CONSTITUCION PROVINCIAL","activo":"S","usuarioCreacion":"ADMIN","usuarioMod":"ADMIN","fechaCreacionLong":201006231358,"fechaModLong":201006231358,"orden":36,"visible":"CP"},"numeroNorma":null,"anioNorma":null,"denominacion":null,"emisor":null,"jurisdiccion":{"codigoTabla":null,"codigoValor":4,"codigoRelacion":130004,"valor":"LA RIOJA","activo":"S","usuarioCreacion":"ADMIN","usuarioMod":"ADMIN","fechaCreacionLong":201006231032,"fechaModLong":201006231032,"orden":null,"visible":null},"articulo":"120","parrafo":null,"inciso":null,"apartado":null,"controlConstitucional":"N","inconstitucional":"N","usuarioCreacion":"JUR202","usuarioModificacion":"JUR202","fechaCreacion":201902281513,"fechaModificacion":201902281513},{"interno":5,"norma":{"codigoTabla":null,"codigoValor":3,"codigoRelacion":110003,"valor":"CONSTITUCION PROVINCIAL","activo":"S","usuarioCreacion":"ADMIN","usuarioMod":"ADMIN","fechaCreacionLong":201006231358,"fechaModLong":201006231358,"orden":36,"visible":"CP"},"numeroNorma":null,"anioNorma":null,"denominacion":null,"emisor":null,"jurisdiccion":{"codigoTabla":null,"codigoValor":4,"codigoRelacion":130004,"valor":"LA RIOJA","activo":"S","usuarioCreacion":"ADMIN","usuarioMod":"ADMIN","fechaCreacionLong":201006231032,"fechaModLong":201006231032,"orden":null,"visible":null},"articulo":"171","parrafo":null,"inciso":null,"apartado":null,"controlConstitucional":"N","inconstitucional":"N","usuarioCreacion":"JUR202","usuarioModificacion":"JUR202","fechaCreacion":201902281513,"fechaModificacion":201902281513},{"interno":6,"norma":{"codigoTabla":null,"codigoValor":7,"codigoRelacion":110007,"valor":"DECRETO PROVINCIAL","activo":"S","usuarioCreacion":"ADMIN","usuarioMod":"ADMIN","fechaCreacionLong":201006231358,"fechaModLong":201006231358,"orden":38,"visible":"DP"},"numeroNorma":1491,"anioNorma":2018,"denominacion":null,"emisor":null,"jurisdiccion":{"codigoTabla":null,"codigoValor":4,"codigoRelacion":130004,"valor":"LA RIOJA","activo":"S","usuarioCreacion":"ADMIN","usuarioMod":"ADMIN","fechaCreacionLong":201006231032,"fechaModLong":201006231032,"orden":null,"visible":null},"articulo":null,"parrafo":null,"inciso":null,"apartado":null,"controlConstitucional":"N","inconstitucional":"N","usuarioCreacion":"JUR202","usuarioModificacion":"JUR202","fechaCreacion":201902281519,"fechaModificacion":201902281519},{"interno":7,"norma":{"codigoTabla":null,"codigoValor":7,"codigoRelacion":110007,"valor":"DECRETO PROVINCIAL","activo":"S","usuarioCreacion":"ADMIN","usuarioMod":"ADMIN","fechaCreacionLong":201006231358,"fechaModLong":201006231358,"orden":38,"visible":"DP"},"numeroNorma":1484,"anioNorma":2018,"denominacion":null,"emisor":null,"jurisdiccion":{"codigoTabla":null,"codigoValor":4,"codigoRelacion":130004,"valor":"LA RIOJA","activo":"S","usuarioCreacion":"ADMIN","usuarioMod":"ADMIN","fechaCreacionLong":201006231032,"fechaModLong":201006231032,"orden":null,"visible":null},"articulo":null,"parrafo":null,"inciso":null,"apartado":null,"controlConstitucional":"N","inconstitucional":"N","usuarioCreacion":"JUR202","usuarioModificacion":"JUR202","fechaCreacion":201902281521,"fechaModificacion":201902281521}],"enlaces":[],"dictamenesProcuracion":null,"votosSumario":[],"votosAnalisisDocumental":[{"id":17020,"ministros":[{"id":69,"tipo":"V","descripcion":"ROSENKRANTZ","orden":2,"activo":"S","codigoRelacion":null,"tipoMinistro":"M","descripcionVacia":""},{"id":2,"tipo":"V","descripcion":"HIGHTON de NOLASCO","orden":5,"activo":"N","codigoRelacion":null,"tipoMinistro":"M","descripcionVacia":""},{"id":5,"tipo":"V","descripcion":"MAQUEDA","orden":3,"activo":"N","codigoRelacion":null,"tipoMinistro":"M","descripcionVacia":""},{"id":1,"tipo":"V","descripcion":"LORENZETTI","orden":3,"activo":"S","codigoRelacion":null,"tipoMinistro":"M","descripcionVacia":""},{"id":68,"tipo":"V","descripcion":"ROSATTI","orden":1,"activo":"S","codigoRelacion":null,"tipoMinistro":"M","descripcionVacia":""}],"tipoVoto":{"id":1,"descripcion":"UNANIMIDAD","descripcionPublica":" "},"nroPagina":null}],"materias":[{"codigoTabla":null,"codigoValor":381,"codigoRelacion":90381,"valor":"CONSTITUCIONAL","activo":"S","usuarioCreacion":"ADMIN","usuarioMod":"SJC287","fechaCreacionLong":201903220948,"fechaModLong":201909170908,"orden":null,"visible":null}],"usuarioCreacion":null,"usuarioCreacionOld":null,"fechaCreacion":201902281509,"usuarioModificacion":{"id":13,"nombreUsuario":"27230157427","apellido":"Lucero","nombre":"Maria Silvina","estado":"A","tieneToken":"N","cargo":null,"fechaModificacion":null,"fechaCreacion":1583847595000,"nombreUsuarioMigrado":null,"codigo":"SJC653","mail":"slucero@csjn.gov.ar","intentos":0,"notificacion":false},"usuarioModificacionOld":null,"fechaModificacion":202009071931,"usuarioControl":null,"usuarioControlOld":null,"fechaControl":null,"expediente":{"id":33124036,"numeroExpediente":125,"anioExpediente":2019,"tomoExpediente":null,"letraExpediente":null,"tipoExpediente":null,"camara":{"id":0,"codigo":"0","abreviatura":"CSJ","descripcion":"Corte Suprema de Justicia de la Nación","estado":0,"descripcionLarga":"CSJ - Corte Suprema de Justicia de la Nación"},"objetoJuicio":{"id":9875,"descripcion":"AMPARO","idMateria":0,"tema":null},"caratula":"UNION CIVICA RADICAL DE LA PROVINCIA DE LA RIOJA Y OTRO c/ LA RIOJA, PROVINCIA DE s/AMPARO","verificacionMesa":"N","etiqueta":null,"hijos":[],"oldIdentificadorExpediente":"125. "},"recursoExpediente":{"id":5526217,"expediente":{"id":33124036,"numeroExpediente":125,"anioExpediente":2019,"tomoExpediente":null,"letraExpediente":null,"tipoExpediente":null,"camara":{"id":0,"codigo":"0","abreviatura":"CSJ","descripcion":"Corte Suprema de Justicia de la Nación","estado":0,"descripcionLarga":"CSJ - Corte Suprema de Justicia de la Nación"},"objetoJuicio":{"id":9875,"descripcion":"AMPARO","idMateria":0,"tema":null},"caratula":"UNION CIVICA RADICAL DE LA PROVINCIA DE LA RIOJA Y OTRO c/ LA RIOJA, PROVINCIA DE s/AMPARO","verificacionMesa":"N","etiqueta":null,"hijos":[],"oldIdentificadorExpediente":"125. "},"tipoRecurso":{"id":1243,"codigo":"CIR","descripcion":"CIRCULACION DEL EXPEDIENTE"},"claveRecurso":null,"identificacionExpediente":"CSJ 125/2019"},"identificacionExpediente":"CSJ 125/2019","stringMayoria":"","stringVoto":"","stringDisidencia":"","stringDisidenciaParcial":"","stringAbstencion":"","stringVotosAnalisis":" ROSENKRANTZ, HIGHTON de NOLASCO, MAQUEDA, LORENZETTI, ROSATTI   ","htmlVotos":"<div class='panel panel-default' onclick='irAPagina(1)' style='padding: 2px;'><div class='panel-body voto btn-link'><div class='row'><div class='col-xs-9 col-sm-8'> ROSENKRANTZ</div></div><div class='row'><div class='col-xs-9 col-sm-8'> HIGHTON de NOLASCO</div></div><div class='row'><div class='col-xs-9 col-sm-8'> MAQUEDA</div></div><div class='row'><div class='col-xs-9 col-sm-8'> LORENZETTI</div></div><div class='row'><div class='col-xs-9 col-sm-8'> ROSATTI</div></div></div></div>"}
