{"id":760857,"competencia":{"codigoTabla":null,"codigoValor":6,"codigoRelacion":190006,"valor":"APELACION EXTRAORDINARIA","activo":"S","usuarioCreacion":"ADMIN","usuarioMod":"ADMIN","fechaCreacionLong":201110290932,"fechaModLong":201110290932,"orden":null,"visible":null},"tipoAccion":null,"sentidoPronunciamiento":{"codigoTabla":null,"codigoValor":4,"codigoRelacion":80004,"valor":"DEJA SIN EFECTO","activo":"S","usuarioCreacion":"ADMIN","usuarioMod":"ADMIN","fechaCreacionLong":201008181259,"fechaModLong":201008181259,"orden":null,"visible":null},"materia":null,"remision":null,"tipoRecurso":{"codigoTabla":null,"codigoValor":1,"codigoRelacion":230001,"valor":"RECURSO DE QUEJA","activo":"S","usuarioCreacion":"ADMIN","usuarioMod":"JUR3WP","fechaCreacionLong":201110290934,"fechaModLong":201111011307,"orden":null,"visible":null},"dependencia":null,"dependenciaHija":null,"publico":"S","materiaSecretaria":{"codigoTabla":null,"codigoValor":6,"codigoRelacion":250006,"valor":"Laboral","activo":"S","usuarioCreacion":"ADMIN","usuarioMod":"ADMIN","fechaCreacionLong":201604041608,"fechaModLong":201604111334,"orden":null,"visible":null},"caratulaFallo":"Melvin, Pablo Andrés c/ INSSJP s/ reclamos varios ","alias":null,"caratula":"Recurso Queja Nº 1 - MELVIN, PABLO ANDRES c/ INSSJP s/RECLAMOS VARIOS","inconstitucional":false,"falloDestacado":{"id":1558,"titulo":"Exceso de competencia al modificar la imposición de las costas","cabecilla":"Jurisdicción de la alzada suscitada solo por el actor al cuestionar el rechazo de la pretensión - Sentencia que impone las costas de ambas instancias a la parte vencida y única recurrente, pese a la ausencia de planteo de la contraria, que no había recurrido el fallo ni formulado manifestación alguna al respecto - Decisión que frustró el derecho de defensa del apelante al colocarlo en una situación más gravosa - Pronunciamiento que se apartó del texto legal, a la vez que excedió los límites de su competencia- Menoscabo de las garantías constitucionales de la defensa en juicio y de propiedad - Se deja sin efecto la sentencia recurrida","esNovedad":true,"fecha":1606359600000,"relevancia":1,"usuarioModificacion":null,"fechaModificacion":null,"usuarioCreacion":null,"fechaCreacion":null,"privado":null,"posicion":null,"resumen":null},"reciboEntrada":{"id":29609,"secretaria":{"id":13,"tipo":"S","descripcion":"Sec. Judicial Nº 6","orden":6,"activo":"S","codigoRelacion":250006,"descripcionWeb":"Laboral","descripcionVacia":""},"reciboEntradaExpedientes":[{"expediente":{"id":32802063,"numeroExpediente":12087871,"anioExpediente":2012,"tomoExpediente":null,"letraExpediente":null,"tipoExpediente":null,"camara":{"id":25,"codigo":"25","abreviatura":"FRO","descripcion":"Justicia Federal de Rosario","estado":0,"descripcionLarga":"FRO - Justicia Federal de Rosario"},"objetoJuicio":{"id":2014,"descripcion":"RECLAMOS VARIOS","idMateria":112,"tema":{"id":8,"codigo":"LABORAL"}},"caratula":"Recurso Queja Nº 1 - MELVIN, PABLO ANDRES c/ INSSJP s/RECLAMOS VARIOS","verificacionMesa":"N","etiqueta":null,"hijos":[],"oldIdentificadorExpediente":"12087871. "},"recurso":{"id":5470258,"expediente":{"id":32802063,"numeroExpediente":12087871,"anioExpediente":2012,"tomoExpediente":null,"letraExpediente":null,"tipoExpediente":null,"camara":{"id":25,"codigo":"25","abreviatura":"FRO","descripcion":"Justicia Federal de Rosario","estado":0,"descripcionLarga":"FRO - Justicia Federal de Rosario"},"objetoJuicio":{"id":2014,"descripcion":"RECLAMOS VARIOS","idMateria":112,"tema":{"id":8,"codigo":"LABORAL"}},"caratula":"Recurso Queja Nº 1 - MELVIN, PABLO ANDRES c/ INSSJP s/RECLAMOS VARIOS","verificacionMesa":"N","etiqueta":null,"hijos":[],"oldIdentificadorExpediente":"12087871. "},"tipoRecurso":{"id":1182,"codigo":"RHX","descripcion":"QUEJA RECURSO EXTRAORDINARIO DENEGADO"},"claveRecurso":"FRO 012087871/2012/1/RH001","identificacionExpediente":"FRO 012087871/2012/1/RH001"},"piezas":3,"urgente":"N","observaciones":null,"usuarioCreacion":null,"usuarioCreacionOld":"JURJ3F","usuarioModificacion":null,"usuarioModificacionOld":"JURJ3F","fechaCreacion":202009300959,"fechaModificacion":202009300959},{"expediente":{"id":34113845,"numeroExpediente":37431,"anioExpediente":2017,"tomoExpediente":null,"letraExpediente":null,"tipoExpediente":null,"camara":{"id":7,"codigo":"7","abreviatura":"CNT","descripcion":"Cámara Nacional de Apelaciones del Trabajo","estado":0,"descripcionLarga":"CNT - Cámara Nacional de Apelaciones del Trabajo"},"objetoJuicio":{"id":9701,"descripcion":"ACCIDENTE - LEY ESPECIAL","idMateria":5,"tema":null},"caratula":"Recurso Queja Nº 1 - FERNANDEZ, RAUL Y OTRO c/ GALENO ART S.A. s/ACCIDENTE - LEY ESPECIAL","verificacionMesa":"N","etiqueta":null,"hijos":[],"oldIdentificadorExpediente":"37431. "},"recurso":{"id":5694757,"expediente":{"id":34113845,"numeroExpediente":37431,"anioExpediente":2017,"tomoExpediente":null,"letraExpediente":null,"tipoExpediente":null,"camara":{"id":7,"codigo":"7","abreviatura":"CNT","descripcion":"Cámara Nacional de Apelaciones del Trabajo","estado":0,"descripcionLarga":"CNT - Cámara Nacional de Apelaciones del Trabajo"},"objetoJuicio":{"id":9701,"descripcion":"ACCIDENTE - LEY ESPECIAL","idMateria":5,"tema":null},"caratula":"Recurso Queja Nº 1 - FERNANDEZ, RAUL Y OTRO c/ GALENO ART S.A. s/ACCIDENTE - LEY ESPECIAL","verificacionMesa":"N","etiqueta":null,"hijos":[],"oldIdentificadorExpediente":"37431. "},"tipoRecurso":{"id":1182,"codigo":"RHX","descripcion":"QUEJA RECURSO EXTRAORDINARIO DENEGADO"},"claveRecurso":"CNT 037431/2017/1/RH001","identificacionExpediente":"CNT 037431/2017/1/RH001"},"piezas":1,"urgente":"N","observaciones":null,"usuarioCreacion":null,"usuarioCreacionOld":"JURJ3F","usuarioModificacion":null,"usuarioModificacionOld":"JURJ3F","fechaCreacion":202009301018,"fechaModificacion":202009301018},{"expediente":{"id":34278155,"numeroExpediente":8118,"anioExpediente":2003,"tomoExpediente":null,"letraExpediente":null,"tipoExpediente":null,"camara":{"id":3,"codigo":"3","abreviatura":"CCF","descripcion":"Cámara Nacional de Apelaciones en lo Civil y Comercial Federal","estado":0,"descripcionLarga":"CCF - Cámara Nacional de Apelaciones en lo Civil y Comercial Federal"},"objetoJuicio":{"id":1216,"descripcion":"PROCESO DE CONOCIMIENTO","idMateria":3,"tema":{"id":451,"codigo":"PROCESOCON"}},"caratula":"Recurso Queja Nº 1 - PANTANO FLORINDO JESUS Y OTROS c/ ESTADO NAC MINIST DE TRABAJO EMPLEO Y FORM REC HUMANOS Y OTROS s/PROCESO DE CONOCIMIENTO","verificacionMesa":"N","etiqueta":null,"hijos":[],"oldIdentificadorExpediente":"8118. "},"recurso":{"id":5729062,"expediente":{"id":34278155,"numeroExpediente":8118,"anioExpediente":2003,"tomoExpediente":null,"letraExpediente":null,"tipoExpediente":null,"camara":{"id":3,"codigo":"3","abreviatura":"CCF","descripcion":"Cámara Nacional de Apelaciones en lo Civil y Comercial Federal","estado":0,"descripcionLarga":"CCF - Cámara Nacional de Apelaciones en lo Civil y Comercial Federal"},"objetoJuicio":{"id":1216,"descripcion":"PROCESO DE CONOCIMIENTO","idMateria":3,"tema":{"id":451,"codigo":"PROCESOCON"}},"caratula":"Recurso Queja Nº 1 - PANTANO FLORINDO JESUS Y OTROS c/ ESTADO NAC MINIST DE TRABAJO EMPLEO Y FORM REC HUMANOS Y OTROS s/PROCESO DE CONOCIMIENTO","verificacionMesa":"N","etiqueta":null,"hijos":[],"oldIdentificadorExpediente":"8118. "},"tipoRecurso":{"id":1182,"codigo":"RHX","descripcion":"QUEJA RECURSO EXTRAORDINARIO DENEGADO"},"claveRecurso":"CCF 008118/2003/1/RH001","identificacionExpediente":"CCF 008118/2003/1/RH001"},"piezas":1,"urgente":"N","observaciones":null,"usuarioCreacion":null,"usuarioCreacionOld":"JURJ3F","usuarioModificacion":null,"usuarioModificacionOld":"JURJ3F","fechaCreacion":202009301000,"fechaModificacion":202009301000}],"fecha":1601434800000,"fechaLong":20200930,"observaciones":null,"codigoUsuario":"JURJ3F","fechaString":"30/09/2020"},"observaciones":null,"comentarios":null,"enPreparacion":null,"formulaDesarrollo":null,"audPublica":"N","articulo16Ley48":"N","inicializacion":"N","amicue_curie":"N","conOpinion":null,"chequeoVoto":"S","cambiaJurisp":null,"sentenciaModelo":null,"citaDoctrina":null,"citaExtranjera":null,"votosOpinion":"N","art11Acordada4":null,"resolucionOriginarios":null,"cuestionesFederales":[{"tipoCuestionFederal":{"codigoTabla":null,"codigoValor":2,"codigoRelacion":50002,"valor":"SENTENCIA ARBITRARIA","activo":"S","usuarioCreacion":"ADMIN","usuarioMod":"JURJ3F","fechaCreacionLong":201006041222,"fechaModLong":202203141533,"orden":null,"visible":null},"usuarioCreacion":"JURJ3F","usuarioModificacion":"JURJ3F","fechaCreacion":202012010836,"fechaModificacion":202012010836}],"formulas":[],"recusExcus":[],"voces":[{"tipoVoz":{"codigoTabla":null,"codigoValor":1242,"codigoRelacion":101242,"valor":"COSTAS","activo":"S","usuarioCreacion":"ADMIN","usuarioMod":"ADMIN","fechaCreacionLong":201006301000,"fechaModLong":201006301000,"orden":null,"visible":null},"orden":1,"usuarioCreacion":"JURJ3F","usuarioModificacion":"JURJ3F","fechaCreacion":202012010836,"fechaModificacion":202012010836},{"tipoVoz":{"codigoTabla":null,"codigoValor":3532,"codigoRelacion":103532,"valor":"SENTENCIA ARBITRARIA","activo":"S","usuarioCreacion":"ADMIN","usuarioMod":"ADMIN","fechaCreacionLong":201006301000,"fechaModLong":201006301000,"orden":null,"visible":null},"orden":2,"usuarioCreacion":"JURJ3F","usuarioModificacion":"JURJ3F","fechaCreacion":202012010836,"fechaModificacion":202012010836},{"tipoVoz":{"codigoTabla":null,"codigoValor":4902,"codigoRelacion":104902,"valor":"LIMITES DEL PRONUNCIAMIENTO","activo":"S","usuarioCreacion":"JUR0V0","usuarioMod":"JUR0V0","fechaCreacionLong":201512281449,"fechaModLong":201512281449,"orden":null,"visible":null},"orden":3,"usuarioCreacion":"JURJ3F","usuarioModificacion":"JURJ3F","fechaCreacion":202012010836,"fechaModificacion":202012010836},{"tipoVoz":{"codigoTabla":null,"codigoValor":4962,"codigoRelacion":104962,"valor":"(*)","activo":"S","usuarioCreacion":"JUR0V0","usuarioMod":"ADMIN","fechaCreacionLong":201903201120,"fechaModLong":201906141011,"orden":null,"visible":null},"orden":4,"usuarioCreacion":"JURJ3F","usuarioModificacion":"JURJ3F","fechaCreacion":202012010836,"fechaModificacion":202012010836},{"tipoVoz":{"codigoTabla":null,"codigoValor":4965,"codigoRelacion":104965,"valor":"(.)","activo":"S","usuarioCreacion":"JUR0V0","usuarioMod":"ADMIN","fechaCreacionLong":201903201221,"fechaModLong":201906141011,"orden":null,"visible":null},"orden":5,"usuarioCreacion":"JURJ3F","usuarioModificacion":"JURJ3F","fechaCreacion":202012010836,"fechaModificacion":202012010836}],"referenciasNormativas":[],"enlaces":[],"dictamenesProcuracion":null,"votosSumario":[],"votosAnalisisDocumental":[{"id":32809,"ministros":[{"id":69,"tipo":"V","descripcion":"ROSENKRANTZ","orden":2,"activo":"S","codigoRelacion":null,"tipoMinistro":"M","descripcionVacia":""},{"id":2,"tipo":"V","descripcion":"HIGHTON de NOLASCO","orden":5,"activo":"N","codigoRelacion":null,"tipoMinistro":"M","descripcionVacia":""},{"id":5,"tipo":"V","descripcion":"MAQUEDA","orden":3,"activo":"N","codigoRelacion":null,"tipoMinistro":"M","descripcionVacia":""},{"id":1,"tipo":"V","descripcion":"LORENZETTI","orden":3,"activo":"S","codigoRelacion":null,"tipoMinistro":"M","descripcionVacia":""}],"tipoVoto":{"id":1,"descripcion":"UNANIMIDAD","descripcionPublica":" "},"nroPagina":null}],"materias":[{"codigoTabla":null,"codigoValor":385,"codigoRelacion":90385,"valor":"PROCESAL","activo":"S","usuarioCreacion":"ADMIN","usuarioMod":"ADMIN","fechaCreacionLong":201903220951,"fechaModLong":201903220951,"orden":null,"visible":null},{"codigoTabla":null,"codigoValor":395,"codigoRelacion":90395,"valor":"LABORAL","activo":"S","usuarioCreacion":"ADMIN","usuarioMod":"ADMIN","fechaCreacionLong":201903221043,"fechaModLong":201903221043,"orden":null,"visible":null}],"usuarioCreacion":null,"usuarioCreacionOld":null,"fechaCreacion":202009301000,"usuarioModificacion":null,"usuarioModificacionOld":null,"fechaModificacion":202012010836,"usuarioControl":null,"usuarioControlOld":null,"fechaControl":null,"expediente":{"id":32802063,"numeroExpediente":12087871,"anioExpediente":2012,"tomoExpediente":null,"letraExpediente":null,"tipoExpediente":null,"camara":{"id":25,"codigo":"25","abreviatura":"FRO","descripcion":"Justicia Federal de Rosario","estado":0,"descripcionLarga":"FRO - Justicia Federal de Rosario"},"objetoJuicio":{"id":2014,"descripcion":"RECLAMOS VARIOS","idMateria":112,"tema":{"id":8,"codigo":"LABORAL"}},"caratula":"Recurso Queja Nº 1 - MELVIN, PABLO ANDRES c/ INSSJP s/RECLAMOS VARIOS","verificacionMesa":"N","etiqueta":null,"hijos":[],"oldIdentificadorExpediente":"12087871. "},"recursoExpediente":{"id":5470258,"expediente":{"id":32802063,"numeroExpediente":12087871,"anioExpediente":2012,"tomoExpediente":null,"letraExpediente":null,"tipoExpediente":null,"camara":{"id":25,"codigo":"25","abreviatura":"FRO","descripcion":"Justicia Federal de Rosario","estado":0,"descripcionLarga":"FRO - Justicia Federal de Rosario"},"objetoJuicio":{"id":2014,"descripcion":"RECLAMOS VARIOS","idMateria":112,"tema":{"id":8,"codigo":"LABORAL"}},"caratula":"Recurso Queja Nº 1 - MELVIN, PABLO ANDRES c/ INSSJP s/RECLAMOS VARIOS","verificacionMesa":"N","etiqueta":null,"hijos":[],"oldIdentificadorExpediente":"12087871. "},"tipoRecurso":{"id":1182,"codigo":"RHX","descripcion":"QUEJA RECURSO EXTRAORDINARIO DENEGADO"},"claveRecurso":"FRO 012087871/2012/1/RH001","identificacionExpediente":"FRO 012087871/2012/1/RH001"},"identificacionExpediente":"FRO 012087871/2012/1/RH001","stringMayoria":"","stringVoto":"","stringDisidencia":"","stringDisidenciaParcial":"","stringAbstencion":"","stringVotosAnalisis":" ROSENKRANTZ, HIGHTON de NOLASCO, MAQUEDA, LORENZETTI   ","htmlVotos":"<div class='panel panel-default' onclick='irAPagina(1)' style='padding: 2px;'><div class='panel-body voto btn-link'><div class='row'><div class='col-xs-9 col-sm-8'> ROSENKRANTZ</div></div><div class='row'><div class='col-xs-9 col-sm-8'> HIGHTON de NOLASCO</div></div><div class='row'><div class='col-xs-9 col-sm-8'> MAQUEDA</div></div><div class='row'><div class='col-xs-9 col-sm-8'> LORENZETTI</div></div></div></div>"}
